<?xml version="1.0" encoding="utf-8"?>
<extension type="module" version="2.5" client="site" method="upgrade">
	<name>mod_jsolr_latest</name>
	<creationDate>2014-02-21</creationDate>
	<author>KnowledgeARC</author>
	<authorEmail>development@knowledgearc.com</authorEmail>
	<authorUrl>http://www.knowledgearc.org</authorUrl>
	<copyright>>Copyright (C) 2014 KnowledgeARC Ltd. All rights reserved.</copyright>
	<license>http://www.gnu.org/licenses/gpl-3.0.html</license>
	<version>1.0.0</version>
	<description>MOD_JSOLR_LATEST_XML_DESCRIPTION</description>
	<files>
		<filename module="mod_jsolr_latest">mod_jsolr_latest.php</filename>
		<filename>helper.php</filename>
		<folder>tmpl</folder>
	</files>

	<languages>
		<language tag="en-GB">language/en-GB/en-GB.mod_jsolr_latest.ini</language>
		<language tag="en-GB">language/en-GB/en-GB.mod_jsolr_latest.sys.ini</language>
	</languages>
    	
    <config>
		<fields name="params">
			<fieldset name="basic" addfieldpath="/libraries/jsolr/form/fields">
				<field
					name="count"
					type="text"
					default="5"
					label="MOD_JSOLR_LATEST_FIELD_COUNT_LABEL"
					description="MOD_JSOLR_LATEST_FIELD_COUNT_DESC"/>
				<field
					name="ordering"
					type="list"
					default="modified"
					label="MOD_JSOLR_LATEST_FIELD_ORDERING_LABEL"
					description="MOD_JSOLR_LATEST_FIELD_ORDERING_DESC">
					<option value="created">MOD_JSOLR_LATEST_VALUE_ADDED</option>
					<option value="modified">MOD_JSOLR_LATEST_VALUE_MODIFIED</option>
				</field>
				<field 
					name="o" 
					type="jsolr.pluginlist"
					label="MOD_JSOLR_LATEST_FIELD_O_LABEL"
					description="MOD_JSOLR_LATEST_FIELD_O_DESC">
					<option value="">MOD_JSOLR_LATEST_VALUE_NONE</option>	
				</field>
				<field
					name="fq"
					type="text"
					label="MOD_JSOLR_LATEST_FIELD_FQ_LABEL"
					description="MOD_JSOLR_LATEST_FIELD_FQ_DESC"/>
			</fieldset>
            <fieldset name="advanced">
                <field
                    name="layout"
                    type="modulelayout"
                    label="JFIELD_ALT_LAYOUT_LABEL"
                    description="JFIELD_ALT_MODULE_LAYOUT_DESC" />
                <field
                    name="moduleclass_sfx"
                    type="text"
                    label="COM_MODULES_FIELD_MODULECLASS_SFX_LABEL"
                    description="COM_MODULES_FIELD_MODULECLASS_SFX_DESC" />
            </fieldset>
        </fields>
    </config>
    
	
	<updateservers>
		<server type="extension" priority="1"><![CDATA[http://knowledgearc.org/index.php?option=com_ars&view=update&task=stream&format=xml&id=13&dummy=extension.xml]]></server>
	</updateservers>
</extension>